dlanalysis/__init__.py
dlanalysis/log/__init__.py
dlanalysis/log/__main__.py
dlanalysis/log/builtins.py
dlanalysis/log/pattern.py
dlanalysis/log/pipeline.py
dlanalysis/log/utils.py
dlanalysis-0.0.1.dist-info/METADATA
dlanalysis-0.0.1.dist-info/WHEEL
dlanalysis-0.0.1.dist-info/top_level.txt
dlanalysis-0.0.1.dist-info/RECORD
