Metadata-Version: 2.1
Name: dlanalysis
Version: 0.0.1
Summary: Toolkit for analysis of deep learning outputs.
Home-page: https://github.com/ultmaster/dlanalysis
Author: Yuge Zhang
Author-email: scottyugochang@gmail.com
License: UNKNOWN
Platform: UNKNOWN
Classifier: Programming Language :: Python :: 3
Classifier: License :: OSI Approved :: MIT License
Classifier: Operating System :: OS Independent
Requires-Python: >=3.6
